frake/AnalysisFunctions.py
frake/Anura3DResults.py
frake/FileFunctions.py
frake/GeotechnicalFunctions.py
frake/GraphFunctions.py
frake/ModifierFunctions.py
frake/SamplingFunctions.py
frake/__init__.py
frake-0.0.3.dist-info/LICENSE
frake-0.0.3.dist-info/METADATA
frake-0.0.3.dist-info/WHEEL
frake-0.0.3.dist-info/top_level.txt
frake-0.0.3.dist-info/RECORD
