Metadata-Version: 2.1
Name: frake
Version: 0.0.3
Summary: Visualizing tool for Anura3D results
Home-page: https://github.com/luisez1988/FRAKE
Author: Luis E. Zambrano-Cruzatty
Author-email: luisez@vt.edu
License: UNKNOWN
Platform: UNKNOWN
Classifier: Programming Language :: Python :: 3
Classifier: License :: OSI Approved :: GNU General Public License v3 (GPLv3)
Classifier: Operating System :: OS Independent
Requires-Python: >=3.6
